LICENSE.txt
MANIFEST.in
README.rst
setup.py
client/__init__.py
client/client.properties
client/util.py
client/sample/__init__.py
client/sample/admin_auth.py
client/sample/auth.py
client/sample/get_account.py
client/zclient/__init__.py
client/zclient/change_passwor.py
client/zclient/get_account_info.py
client/zclient/get_info.py
client/zclient/get_proxied_info.py
pyzimbra/__init__.py
pyzimbra/auth.py
pyzimbra/base.py
pyzimbra/sconstant.py
pyzimbra/soap.py
pyzimbra/soap_auth.py
pyzimbra/soap_soappy.py
pyzimbra/soap_transport.py
pyzimbra/util.py
pyzimbra/zclient.py
pyzimbra/zconstant.py
pyzimbra.egg-info/PKG-INFO
pyzimbra.egg-info/SOURCES.txt
pyzimbra.egg-info/dependency_links.txt
pyzimbra.egg-info/requires.txt
pyzimbra.egg-info/top_level.txt
pyzimbra/z/__init__.py
pyzimbra/z/admin.py
pyzimbra/z/client.py
pyzimbra/z/zobject/__init__.py
pyzimbra/z/zobject/account.py