Metadata-Version: 1.0
Name: pyzimbra
Version: 0.1
Summary: Zimbra Python Client
Home-page: http://github.com/ilgarm/pyzimbra
Author: Ilgar Mashayev
Author-email: pyzimbra@lab.az
License: LGPL
Platform: UNKNOWN
